<annotation>
	<folder>data_images</folder>
	<filename>233.jpg</filename>
	<path>E:\yolo detection tut\Notes\1_datapreparation\data_images\233.jpg</path>
	<source>
		<database>Unknown</database>
	</source>
	<size>
		<width>425</width>
		<height>425</height>
		<depth>3</depth>
	</size>
	<segmented>0</segmented>
	<object>
		<name>Reflective vest</name>
		<pose>Unspecified</pose>
		<truncated>0</truncated>
		<difficult>0</difficult>
		<bndbox>
			<xmin>78</xmin>
			<ymin>23</ymin>
			<xmax>344</xmax>
			<ymax>401</ymax>
		</bndbox>
	</object>
</annotation>
