<annotation>
	<folder>data_images</folder>
	<filename>561.jpg</filename>
	<path>E:\yolo detection tut\Notes2\1_datapreparation\data_images\561.jpg</path>
	<source>
		<database>Unknown</database>
	</source>
	<size>
		<width>1280</width>
		<height>720</height>
		<depth>3</depth>
	</size>
	<segmented>0</segmented>
	<object>
		<name>Helmet</name>
		<pose>Unspecified</pose>
		<truncated>1</truncated>
		<difficult>0</difficult>
		<bndbox>
			<xmin>487</xmin>
			<ymin>1</ymin>
			<xmax>616</xmax>
			<ymax>174</ymax>
		</bndbox>
	</object>
	<object>
		<name>Reflective vest</name>
		<pose>Unspecified</pose>
		<truncated>0</truncated>
		<difficult>0</difficult>
		<bndbox>
			<xmin>399</xmin>
			<ymin>87</ymin>
			<xmax>630</xmax>
			<ymax>346</ymax>
		</bndbox>
	</object>
	<object>
		<name>Reflective vest</name>
		<pose>Unspecified</pose>
		<truncated>0</truncated>
		<difficult>0</difficult>
		<bndbox>
			<xmin>831</xmin>
			<ymin>60</ymin>
			<xmax>1073</xmax>
			<ymax>370</ymax>
		</bndbox>
	</object>
</annotation>
