<annotation>
	<folder>data_images</folder>
	<filename>953.jpg</filename>
	<path>E:\yolo detection tut\Notes\1_datapreparation\data_images\953.jpg</path>
	<source>
		<database>Unknown</database>
	</source>
	<size>
		<width>1280</width>
		<height>720</height>
		<depth>3</depth>
	</size>
	<segmented>0</segmented>
	<object>
		<name>Reflective vest</name>
		<pose>Unspecified</pose>
		<truncated>0</truncated>
		<difficult>0</difficult>
		<bndbox>
			<xmin>408</xmin>
			<ymin>89</ymin>
			<xmax>597</xmax>
			<ymax>243</ymax>
		</bndbox>
	</object>
	<object>
		<name>No helmet</name>
		<pose>Unspecified</pose>
		<truncated>0</truncated>
		<difficult>0</difficult>
		<bndbox>
			<xmin>494</xmin>
			<ymin>13</ymin>
			<xmax>612</xmax>
			<ymax>139</ymax>
		</bndbox>
	</object>
</annotation>
