<annotation>
	<folder>data_images</folder>
	<filename>982.jpg</filename>
	<path>E:\yolo detection tut\Notes2\1_datapreparation\data_images\982.jpg</path>
	<source>
		<database>Unknown</database>
	</source>
	<size>
		<width>4500</width>
		<height>3000</height>
		<depth>3</depth>
	</size>
	<segmented>0</segmented>
	<object>
		<name>Helmet</name>
		<pose>Unspecified</pose>
		<truncated>0</truncated>
		<difficult>0</difficult>
		<bndbox>
			<xmin>1606</xmin>
			<ymin>231</ymin>
			<xmax>2456</xmax>
			<ymax>1476</ymax>
		</bndbox>
	</object>
	<object>
		<name>Reflective vest</name>
		<pose>Unspecified</pose>
		<truncated>1</truncated>
		<difficult>0</difficult>
		<bndbox>
			<xmin>1100</xmin>
			<ymin>1358</ymin>
			<xmax>2751</xmax>
			<ymax>3000</ymax>
		</bndbox>
	</object>
</annotation>
